[
    {
        "personaggio": "Anorel",
        "ruolo": "Portiere",
        "stagione": "3",
        "link_immagine": "C:\\Users\\aless\\Desktop\\Inazuma\\Portieri\\Portieri inazuma 3\\Anorel-inazuma-3.webp"
    },
    {
        "personaggio": "Astaroth",
        "ruolo": "Portiere",
        "stagione": "3",
        "link_immagine": "C:\\Users\\aless\\Desktop\\Inazuma\\Portieri\\Portieri inazuma 3\\Astaroth-inazuma-3.webp"
    },
    {
        "personaggio": "Baloi",
        "ruolo": "Portiere",
        "stagione": "3",
        "link_immagine": "C:\\Users\\aless\\Desktop\\Inazuma\\Portieri\\Portieri inazuma 3\\Baloi-inazuma-3.webp"
    },
    {
        "personaggio": "Bear",
        "ruolo": "Portiere",
        "stagione": "3",
        "link_immagine": "C:\\Users\\aless\\Desktop\\Inazuma\\Portieri\\Portieri inazuma 3\\Bear-inazuma-3.webp"
    },
    {
        "personaggio": "Blasi",
        "ruolo": "Portiere",
        "stagione": "3",
        "link_immagine": "C:\\Users\\aless\\Desktop\\Inazuma\\Portieri\\Portieri inazuma 3\\Blasi-inazuma-3.webp"
    },
    {
        "personaggio": "C",
        "ruolo": "Portiere",
        "stagione": "3",
        "link_immagine": "C:\\Users\\aless\\Desktop\\Inazuma\\Portieri\\Portieri inazuma 3\\C-Horse-inazuma-3.webp"
    },
    {
        "personaggio": "Civet",
        "ruolo": "Portiere",
        "stagione": "3",
        "link_immagine": "C:\\Users\\aless\\Desktop\\Inazuma\\Portieri\\Portieri inazuma 3\\Civet-inazuma-3.webp"
    },
    {
        "personaggio": "Cruz",
        "ruolo": "Portiere",
        "stagione": "3",
        "link_immagine": "C:\\Users\\aless\\Desktop\\Inazuma\\Portieri\\Portieri inazuma 3\\Cruz-inazuma-3.webp"
    },
    {
        "personaggio": "da",
        "ruolo": "Portiere",
        "stagione": "3",
        "link_immagine": "C:\\Users\\aless\\Desktop\\Inazuma\\Portieri\\Portieri inazuma 3\\da-Silva-inazuma-3.webp"
    },
    {
        "personaggio": "Dash",
        "ruolo": "Portiere",
        "stagione": "3",
        "link_immagine": "C:\\Users\\aless\\Desktop\\Inazuma\\Portieri\\Portieri inazuma 3\\Dash-inazuma-3.webp"
    },
    {
        "personaggio": "Enders",
        "ruolo": "Portiere",
        "stagione": "3",
        "link_immagine": "C:\\Users\\aless\\Desktop\\Inazuma\\Portieri\\Portieri inazuma 3\\Enders-inazuma-3.webp"
    },
    {
        "personaggio": "Espind",
        "ruolo": "Portiere",
        "stagione": "3",
        "link_immagine": "C:\\Users\\aless\\Desktop\\Inazuma\\Portieri\\Portieri inazuma 3\\Espind-inazuma-3.webp"
    },
    {
        "personaggio": "Hamad",
        "ruolo": "Portiere",
        "stagione": "3",
        "link_immagine": "C:\\Users\\aless\\Desktop\\Inazuma\\Portieri\\Portieri inazuma 3\\Hamad-inazuma-3.webp"
    },
    {
        "personaggio": "Hawke",
        "ruolo": "Portiere",
        "stagione": "3",
        "link_immagine": "C:\\Users\\aless\\Desktop\\Inazuma\\Portieri\\Portieri inazuma 3\\Hawke-inazuma-3.webp"
    },
    {
        "personaggio": "Helio",
        "ruolo": "Portiere",
        "stagione": "3",
        "link_immagine": "C:\\Users\\aless\\Desktop\\Inazuma\\Portieri\\Portieri inazuma 3\\Helio-inazuma-3.webp"
    },
    {
        "personaggio": "Helio",
        "ruolo": "Portiere",
        "stagione": "3",
        "link_immagine": "C:\\Users\\aless\\Desktop\\Inazuma\\Portieri\\Portieri inazuma 3\\Helio-jr-inazuma-3.webp"
    },
    {
        "personaggio": "Ho",
        "ruolo": "Portiere",
        "stagione": "3",
        "link_immagine": "C:\\Users\\aless\\Desktop\\Inazuma\\Portieri\\Portieri inazuma 3\\Ho-inazuma-3.webp"
    },
    {
        "personaggio": "Jeeves",
        "ruolo": "Portiere",
        "stagione": "3",
        "link_immagine": "C:\\Users\\aless\\Desktop\\Inazuma\\Portieri\\Portieri inazuma 3\\Jeeves-inazuma-3.webp"
    },
    {
        "personaggio": "Jeongsu",
        "ruolo": "Portiere",
        "stagione": "3",
        "link_immagine": "C:\\Users\\aless\\Desktop\\Inazuma\\Portieri\\Portieri inazuma 3\\Jeongsu-inazuma-3.webp"
    },
    {
        "personaggio": "Keenan",
        "ruolo": "Portiere",
        "stagione": "3",
        "link_immagine": "C:\\Users\\aless\\Desktop\\Inazuma\\Portieri\\Portieri inazuma 3\\Keenan-inazuma-3.webp"
    },
    {
        "personaggio": "Lazare",
        "ruolo": "Portiere",
        "stagione": "3",
        "link_immagine": "C:\\Users\\aless\\Desktop\\Inazuma\\Portieri\\Portieri inazuma 3\\Lazare-inazuma-3.webp"
    },
    {
        "personaggio": "Lazuli",
        "ruolo": "Portiere",
        "stagione": "3",
        "link_immagine": "C:\\Users\\aless\\Desktop\\Inazuma\\Portieri\\Portieri inazuma 3\\Lazuli-inazuma-3.webp"
    },
    {
        "personaggio": "Lucefar",
        "ruolo": "Portiere",
        "stagione": "3",
        "link_immagine": "C:\\Users\\aless\\Desktop\\Inazuma\\Portieri\\Portieri inazuma 3\\Lucefar-inazuma-3.webp"
    },
    {
        "personaggio": "Makebe",
        "ruolo": "Portiere",
        "stagione": "3",
        "link_immagine": "C:\\Users\\aless\\Desktop\\Inazuma\\Portieri\\Portieri inazuma 3\\Makebe-inazuma-3.webp"
    },
    {
        "personaggio": "McQueen",
        "ruolo": "Portiere",
        "stagione": "3",
        "link_immagine": "C:\\Users\\aless\\Desktop\\Inazuma\\Portieri\\Portieri inazuma 3\\McQueen-inazuma-3.webp"
    },
    {
        "personaggio": "Mustafa",
        "ruolo": "Portiere",
        "stagione": "3",
        "link_immagine": "C:\\Users\\aless\\Desktop\\Inazuma\\Portieri\\Portieri inazuma 3\\Mustafa-inazuma-3.webp"
    },
    {
        "personaggio": "Ortega",
        "ruolo": "Portiere",
        "stagione": "3",
        "link_immagine": "C:\\Users\\aless\\Desktop\\Inazuma\\Portieri\\Portieri inazuma 3\\Ortega-inazuma-3.webp"
    },
    {
        "personaggio": "Pialat",
        "ruolo": "Portiere",
        "stagione": "3",
        "link_immagine": "C:\\Users\\aless\\Desktop\\Inazuma\\Portieri\\Portieri inazuma 3\\Pialat-inazuma-3.webp"
    },
    {
        "personaggio": "Quarzo",
        "ruolo": "Portiere",
        "stagione": "3",
        "link_immagine": "C:\\Users\\aless\\Desktop\\Inazuma\\Portieri\\Portieri inazuma 3\\Quarzo-inazuma-3.webp"
    },
    {
        "personaggio": "Ribeiro",
        "ruolo": "Portiere",
        "stagione": "3",
        "link_immagine": "C:\\Users\\aless\\Desktop\\Inazuma\\Portieri\\Portieri inazuma 3\\Ribeiro-inazuma-3.webp"
    },
    {
        "personaggio": "Sanchez",
        "ruolo": "Portiere",
        "stagione": "3",
        "link_immagine": "C:\\Users\\aless\\Desktop\\Inazuma\\Portieri\\Portieri inazuma 3\\Sanchez-inazuma-3.webp"
    },
    {
        "personaggio": "Sanctis",
        "ruolo": "Portiere",
        "stagione": "3",
        "link_immagine": "C:\\Users\\aless\\Desktop\\Inazuma\\Portieri\\Portieri inazuma 3\\Sanctis-inazuma-3.webp"
    },
    {
        "personaggio": "Welger",
        "ruolo": "Portiere",
        "stagione": "3",
        "link_immagine": "C:\\Users\\aless\\Desktop\\Inazuma\\Portieri\\Portieri inazuma 3\\Welger-inazuma-3.webp"
    },
    {
        "personaggio": "Whale",
        "ruolo": "Portiere",
        "stagione": "3",
        "link_immagine": "C:\\Users\\aless\\Desktop\\Inazuma\\Portieri\\Portieri inazuma 3\\Whale-inazuma-3.webp"
    }
]